HyresBuilder/Geometry.py
HyresBuilder/HyresBuilder.py
HyresBuilder/HyresFF.py
HyresBuilder/RNAbuilder.py
HyresBuilder/__init__.py
HyresBuilder/map/A.map
HyresBuilder/map/C.map
HyresBuilder/map/G.map
HyresBuilder/map/U.map
HyresBuilder-2.3.3.dist-info/LICENSE
HyresBuilder-2.3.3.dist-info/METADATA
HyresBuilder-2.3.3.dist-info/WHEEL
HyresBuilder-2.3.3.dist-info/top_level.txt
HyresBuilder-2.3.3.dist-info/RECORD
